{
  "ComponentIndexes": {
    "com_NumberOfPlayers": 6,
    "comMyRoll": 6,
    "comMyRoll_2": 2,
    "GridTile": 8,
    "numberControl": 7
  },
  "ControlUniqueGuids": {},
  "ControlUniqueIds": {
    "App": 1,
    "Bonus Scores": 114,
    "btn_dev_Achievements": 76,
    "btn_devGameOver": 73,
    "btn_devHighScores": 74,
    "btn_devHighScores_1": 65,
    "btn_devHowToPlay": 71,
    "btn_devNewHighScore": 75,
    "btn_devPlay": 70,
    "btn_devSettings": 72,
    "btn_devTitle": 69,
    "btn_GameOver_PlayAgain": 175,
    "btn_PlayerConfig_Next": 147,
    "btn_PlayGame": 174,
    "btn_Shared_HowToPlay": 173,
    "btn_Start_HowToPlay": 162,
    "btn_Start_NewGame": 146,
    "btnDown": 6,
    "btnF": 170,
    "btnFarkle_Letters": 138,
    "btnKeepDice": 135,
    "btnLastRoundMessage": 125,
    "btnNextPlayer": 127,
    "btnOK": 148,
    "btnRemoveDice": 143,
    "btnRollDice": 150,
    "btnScoreIt": 152,
    "btnScoringBackground": 151,
    "btnUp": 8,
    "Button1": 52,
    "Button2": 53,
    "Circle1": 172,
    "com_NumberOfPlayers": 128,
    "comMyRoll": 3,
    "comMyRoll_2": 153,
    "Developer Screen": 66,
    "Dropdown1": 64,
    "Dropdown1_1": 45,
    "FARKLE": 136,
    "gal_FarkleCount": 168,
    "gal_PlayerConfig_Names": 92,
    "gal_PlayersScores": 163,
    "galBonusScoring": 109,
    "Gallery1": 59,
    "Gallery1_1": 30,
    "Gallery1_2": 40,
    "Gallery1_3": 46,
    "Gallery4": 21,
    "Gallery7": 18,
    "Gallery8": 24,
    "Gallery8_1": 118,
    "galleryTemplate1": 93,
    "galleryTemplate2": 60,
    "galleryTemplate2_1": 31,
    "galleryTemplate2_2": 41,
    "galleryTemplate2_3": 47,
    "galleryTemplate3": 164,
    "galleryTemplate32_2": 131,
    "galleryTemplate32_3": 137,
    "galleryTemplate33_1": 110,
    "galleryTemplate4": 169,
    "galleryTemplate5": 22,
    "galleryTemplate5_1": 116,
    "galleryTemplate6": 140,
    "galleryTemplate8": 19,
    "galleryTemplate8_1": 98,
    "galleryTemplate9": 25,
    "galleryTemplate9_1": 119,
    "galMyKeptDice": 139,
    "galMyRoll": 130,
    "galScoreHistory": 115,
    "galScoreHistPlyName": 97,
    "Game Screen": 78,
    "GridTile": 9,
    "grp_currentScreen": 77,
    "grp_GameOver": 186,
    "grp_HowToPlay": 187,
    "grp_LastRoundMessage": 183,
    "grp_Play": 180,
    "grp_Shared": 185,
    "grp_StartScreen": 184,
    "grpDebug": 181,
    "grpPlayerSettings": 55,
    "grpRollTesting": 182,
    "grpScoreSettings": 54,
    "grpSettings": 179,
    "html_BoxShadow": 133,
    "html_BoxShadow_1": 141,
    "html_HowToPlay_Bkgd": 85,
    "ico_PlayerConfig_Back": 88,
    "ico_ScoringSettings": 176,
    "icoBack": 17,
    "icoBack_1": 29,
    "icoBack_2": 57,
    "icoBack_3": 90,
    "icoBack_4": 37,
    "icoBack_5": 39,
    "icon_shared_achievements": 81,
    "icon_shared_achievements_1": 87,
    "icon_Shared_HighScores": 82,
    "icon_Shared_Settings": 83,
    "Icon4": 171,
    "icoPlayerSettings": 177,
    "icoSavePlayerChange": 35,
    "icoSavePlayerChange_1": 51,
    "icoScoreable": 132,
    "icoScoringHistory": 178,
    "img_bkgd_table": 79,
    "imgDice": 134,
    "imgDice_Kept": 142,
    "Label10": 23,
    "Label10_1": 117,
    "Label11": 165,
    "Label12": 166,
    "Label12_1": 61,
    "Label12_2": 42,
    "Label12_3": 32,
    "Label12_4": 33,
    "Label12_5": 48,
    "Label12_6": 49,
    "Label13": 167,
    "Label14": 58,
    "Label14_1": 38,
    "Label20": 20,
    "Label20_1": 99,
    "Label22": 26,
    "Label22_1": 120,
    "Label40_1": 112,
    "Label40_2": 113,
    "Label41_1": 111,
    "Label5_3": 154,
    "Label5_4": 156,
    "Label5_5": 160,
    "Label6_2": 155,
    "Label6_3": 159,
    "Label9": 4,
    "lbl_bonus": 14,
    "lbl_colMyRoll_KeptCount": 105,
    "lbl_colMyRollCount": 104,
    "lbl_currentScreen": 68,
    "lbl_CurrPlayer": 108,
    "lbl_devScreenTitle": 67,
    "lbl_GameOver": 145,
    "lbl_GameOver_Points": 100,
    "lbl_GameOver_Title": 89,
    "lbl_grid": 10,
    "lbl_HowToPlay_Close": 86,
    "lbl_ModCountRows(colMyRoll_Kept)": 101,
    "lbl_overlay": 12,
    "lbl_PlayerConfig_NumberOfPlayers": 126,
    "lbl_PlayerConfigNames_PlayerName": 94,
    "lbl_points": 15,
    "lbl_tile": 11,
    "lbl_varComboPts": 106,
    "lbl_varDiceAvailable": 102,
    "lbl_varRollCount": 103,
    "lbl_varRound": 107,
    "lblOpeningPtsNeeded": 161,
    "lblPlayersTurn": 129,
    "lblProbability": 149,
    "lblTestRoll": 124,
    "numberControl": 5,
    "Player Settings Screen": 28,
    "Rectangle1_1": 158,
    "Rectangle2": 27,
    "Rectangle2_1": 121,
    "Score History Screen": 16,
    "Scoring Settings Screen": 56,
    "Screen1": 36,
    "shp_PlayerConfigNames_Separator": 96,
    "shp_StartScreen_Background": 84,
    "shpLastRoundMessageBackground": 80,
    "shpRollEndMarker": 144,
    "tbNumber": 7,
    "TextInput1": 62,
    "TextInput1_1": 43,
    "tglEnabled": 63,
    "tglEnabled_1": 44,
    "tglTestRoll_1": 123,
    "tmr_clicked": 13,
    "tmr_Farkle": 91,
    "tmr_RollTimer": 157,
    "txt_PlayerConfigNames_PlayerName": 95,
    "txtPlayerName": 34,
    "txtPlayerName_1": 50,
    "txtTestRoll_1": 122
  },
  "FunctionParamsInvariantScripts": {},
  "FunctionParamsInvariantScriptsOnInstances": {},
  "HeaderLastSavedDateTimeUTC": "08/26/2022 16:58:04",
  "IsLegacyComponentAllowGlobalScopeCase": false,
  "LocalConnectionIDReferences": {},
  "LocalDatabaseReferencesAsEmpty": false,
  "LocalResourceFileNames": {
    "bkgd_City": "e97dacce-5e1f-447a-b997-90fe58e4b5fb.jpg",
    "cozy_living_room-wallpaper-1920x1080": "50b8a34b-fa8d-4f30-9d1f-f386ba9872d8.jpg",
    "Table": "08781631-0e23-451c-8c6f-496dc53f05ac.svg"
  },
  "LocalResourceRootPaths": {
    "bkgd_City": "https://docserverpwaprodwus.blob.core.windows.net/fbd06a44-7ea3-40c7-b769-9e42867ec088-1/resource/Assets0Images0e97dacce-5e1f-447a-b997-90fe58e4b5fb.jpg?sv=2017-04-17&sr=b&sig=QnlTt7hLxbepHq9Hie8WabaS5dGOHjyWbmms7wYJcbI%3D&spr=https&se=2022-08-27T17%3A09%3A00Z&sp=r",
    "cozy_living_room-wallpaper-1920x1080": "https://docserverpwaprodwus.blob.core.windows.net/fbd06a44-7ea3-40c7-b769-9e42867ec088-1/resource/Assets0Images050b8a34b-fa8d-4f30-9d1f-f386ba9872d8.jpg?sv=2017-04-17&sr=b&sig=k6cRkIQUHROp3HIdAI2pui1ENM3A0AUSIDuZvXBSlAM%3D&spr=https&se=2022-08-27T17%3A09%3A00Z&sp=r",
    "Table": "https://docserverpwaprodwus.blob.core.windows.net/fbd06a44-7ea3-40c7-b769-9e42867ec088-1/resource/Assets0Images008781631-0e23-451c-8c6f-496dc53f05ac.svg?sv=2017-04-17&sr=b&sig=gaGojfFFBTt3Rn6VWkkhDP7nEE%2FbE%2B2G%2F3I%2BzLKQ%2BMc%3D&spr=https&se=2022-08-27T17%3A09%3A00Z&sp=r"
  },
  "OldLogoFileName": "fimutzga.jpg",
  "OrderComponentMetadata": {
    "2ee30dc81626408eb5290d2c037559d5": 1,
    "346ab8d173664f849d62fb9f8ca81e51": 2,
    "4fb8b76ca030427cbb8e5cb52552fedb": 0
  },
  "OrderComponentTemplate": {
    "2ee30dc81626408eb5290d2c037559d5": 1,
    "346ab8d173664f849d62fb9f8ca81e51": 2,
    "4fb8b76ca030427cbb8e5cb52552fedb": 0
  },
  "OrderDataSource": {
    "colMyRoll": 4,
    "colMyRoll_Kept": 11,
    "colPlayers": 6,
    "colScoringHistory": 3,
    "colScoringTable": 10,
    "coMyRoll_Kept": 5,
    "CustomGallerySample": 0,
    "DropDownSample": 1,
    "gameAchievements": 2,
    "highScores": 8,
    "mygameScoring": 7,
    "myScoring": 9
  },
  "OrderGroupControls": {
    "grp_currentScreen": {
      "btn_dev_Achievements": 0,
      "btn_devGameOver": 7,
      "btn_devHighScores": 8,
      "btn_devHowToPlay": 5,
      "btn_devNewHighScore": 1,
      "btn_devPlay": 4,
      "btn_devSettings": 6,
      "btn_devTitle": 3,
      "lbl_currentScreen": 2
    },
    "grp_GameOver": {
      "btn_GameOver_PlayAgain": 0,
      "galScoreHistory": 4,
      "galScoreHistPlyName": 2,
      "icoBack_3": 3,
      "lbl_GameOver": 1,
      "lbl_GameOver_Points": 6,
      "lbl_GameOver_Title": 5
    },
    "grp_HowToPlay": {
      "html_HowToPlay_Bkgd": 0,
      "lbl_HowToPlay_Close": 1
    },
    "grp_LastRoundMessage": {
      "btnLastRoundMessage": 1,
      "btnOK": 0,
      "shpLastRoundMessageBackground": 2
    },
    "grp_Play": {
      "btnRollDice": 6,
      "btnScoreIt": 8,
      "btnScoringBackground": 15,
      "FARKLE": 2,
      "gal_PlayersScores": 16,
      "galMyKeptDice": 3,
      "galMyRoll": 4,
      "Label5_3": 9,
      "Label5_4": 10,
      "Label5_5": 13,
      "Label6_2": 11,
      "Label6_3": 12,
      "lblOpeningPtsNeeded": 0,
      "lblPlayersTurn": 1,
      "lblProbability": 5,
      "Rectangle1_1": 14,
      "tmr_RollTimer": 7
    },
    "grp_Shared": {
      "btn_Shared_HowToPlay": 1,
      "icon_shared_achievements": 0,
      "icon_Shared_HighScores": 2,
      "icon_Shared_Settings": 3
    },
    "grp_StartScreen": {
      "btn_PlayerConfig_Next": 4,
      "btn_PlayGame": 0,
      "btn_Start_HowToPlay": 6,
      "btn_Start_NewGame": 7,
      "com_NumberOfPlayers": 5,
      "gal_PlayerConfig_Names": 3,
      "ico_PlayerConfig_Back": 1,
      "lbl_PlayerConfig_NumberOfPlayers": 2,
      "shp_StartScreen_Background": 8
    },
    "grpDebug": {
      "Bonus Scores": 8,
      "galBonusScoring": 9,
      "lbl_colMyRoll_KeptCount": 3,
      "lbl_colMyRollCount": 4,
      "lbl_CurrPlayer": 0,
      "lbl_ModCountRows(colMyRoll_Kept)": 7,
      "lbl_varComboPts": 2,
      "lbl_varDiceAvailable": 6,
      "lbl_varRollCount": 5,
      "lbl_varRound": 1
    },
    "grpPlayerSettings": {
      "Gallery1_3": 0,
      "icoBack_5": 1
    },
    "grpRollTesting": {
      "lblTestRoll": 2,
      "tglTestRoll_1": 1,
      "txtTestRoll_1": 0
    },
    "grpScoreSettings": {
      "Gallery1_2": 0,
      "icoBack_4": 1,
      "Label14_1": 2
    },
    "grpSettings": {
      "ico_ScoringSettings": 0,
      "icoPlayerSettings": 2,
      "icoScoringHistory": 1
    }
  },
  "OrderPcfTemplate": {},
  "OrderTemplate": {},
  "OrderXMLTemplate": {
    "button": 7,
    "circle": 12,
    "dropdown": 6,
    "gallery": 1,
    "htmlViewer": 10,
    "icon": 0,
    "image": 8,
    "label": 2,
    "rectangle": 3,
    "star": 9,
    "text": 4,
    "timer": 11,
    "toggleSwitch": 5
  },
  "PublishOrderIndices": {
    "App": 0,
    "Bonus Scores": 40,
    "btn_dev_Achievements": 165,
    "btn_devGameOver": 162,
    "btn_devHighScores": 163,
    "btn_devHighScores_1": 128,
    "btn_devHowToPlay": 160,
    "btn_devNewHighScore": 164,
    "btn_devPlay": 159,
    "btn_devSettings": 161,
    "btn_devTitle": 158,
    "btn_GameOver_PlayAgain": 104,
    "btn_PlayerConfig_Next": 76,
    "btn_PlayGame": 103,
    "btn_Shared_HowToPlay": 102,
    "btn_Start_HowToPlay": 91,
    "btn_Start_NewGame": 75,
    "btnDown": 167,
    "btnF": 99,
    "btnFarkle_Letters": 67,
    "btnKeepDice": 64,
    "btnLastRoundMessage": 53,
    "btnNextPlayer": 55,
    "btnOK": 77,
    "btnRemoveDice": 72,
    "btnRollDice": 79,
    "btnScoreIt": 81,
    "btnScoringBackground": 80,
    "btnUp": 169,
    "Button1": 153,
    "Button2": 154,
    "Circle1": 101,
    "com_NumberOfPlayers": 56,
    "comMyRoll": 0,
    "comMyRoll_2": 82,
    "Developer Screen": 0,
    "Dropdown1": 127,
    "Dropdown1_1": 146,
    "FARKLE": 65,
    "gal_FarkleCount": 97,
    "gal_PlayerConfig_Names": 18,
    "gal_PlayersScores": 92,
    "galBonusScoring": 35,
    "Gallery1": 122,
    "Gallery1_1": 130,
    "Gallery1_2": 141,
    "Gallery1_3": 147,
    "Gallery4": 113,
    "Gallery7": 110,
    "Gallery8": 116,
    "Gallery8_1": 45,
    "galleryTemplate1": 19,
    "galleryTemplate2": 123,
    "galleryTemplate2_1": 131,
    "galleryTemplate2_2": 142,
    "galleryTemplate2_3": 148,
    "galleryTemplate3": 93,
    "galleryTemplate32_2": 60,
    "galleryTemplate32_3": 66,
    "galleryTemplate33_1": 36,
    "galleryTemplate4": 98,
    "galleryTemplate5": 114,
    "galleryTemplate5_1": 43,
    "galleryTemplate6": 69,
    "galleryTemplate8": 111,
    "galleryTemplate8_1": 24,
    "galleryTemplate9": 117,
    "galleryTemplate9_1": 46,
    "galMyKeptDice": 68,
    "galMyRoll": 59,
    "galScoreHistory": 42,
    "galScoreHistPlyName": 23,
    "Game Screen": 0,
    "GridTile": 87,
    "grp_currentScreen": 156,
    "grp_GameOver": 15,
    "grp_HowToPlay": 10,
    "grp_LastRoundMessage": 2,
    "grp_Play": 58,
    "grp_Shared": 4,
    "grp_StartScreen": 7,
    "grpDebug": 41,
    "grpPlayerSettings": 140,
    "grpRollTesting": 50,
    "grpScoreSettings": 139,
    "grpSettings": 106,
    "html_BoxShadow": 62,
    "html_BoxShadow_1": 70,
    "html_HowToPlay_Bkgd": 9,
    "ico_PlayerConfig_Back": 13,
    "ico_ScoringSettings": 105,
    "icoBack": 109,
    "icoBack_1": 129,
    "icoBack_2": 120,
    "icoBack_3": 16,
    "icoBack_4": 136,
    "icoBack_5": 138,
    "icon_shared_achievements": 3,
    "icon_shared_achievements_1": 12,
    "icon_Shared_HighScores": 5,
    "icon_Shared_Settings": 6,
    "Icon4": 100,
    "icoPlayerSettings": 107,
    "icoSavePlayerChange": 135,
    "icoSavePlayerChange_1": 152,
    "icoScoreable": 61,
    "icoScoringHistory": 108,
    "img_bkgd_table": 0,
    "imgDice": 63,
    "imgDice_Kept": 71,
    "Label10": 115,
    "Label10_1": 44,
    "Label11": 94,
    "Label12": 95,
    "Label12_1": 124,
    "Label12_2": 143,
    "Label12_3": 132,
    "Label12_4": 133,
    "Label12_5": 149,
    "Label12_6": 150,
    "Label13": 96,
    "Label14": 121,
    "Label14_1": 137,
    "Label20": 112,
    "Label20_1": 25,
    "Label22": 118,
    "Label22_1": 47,
    "Label40_1": 38,
    "Label40_2": 39,
    "Label41_1": 37,
    "Label5_3": 83,
    "Label5_4": 85,
    "Label5_5": 89,
    "Label6_2": 84,
    "Label6_3": 88,
    "Label9": 166,
    "lbl_bonus": 174,
    "lbl_colMyRoll_KeptCount": 31,
    "lbl_colMyRollCount": 30,
    "lbl_currentScreen": 157,
    "lbl_CurrPlayer": 34,
    "lbl_devScreenTitle": 155,
    "lbl_GameOver": 74,
    "lbl_GameOver_Points": 26,
    "lbl_GameOver_Title": 14,
    "lbl_grid": 170,
    "lbl_HowToPlay_Close": 11,
    "lbl_ModCountRows(colMyRoll_Kept)": 27,
    "lbl_overlay": 172,
    "lbl_PlayerConfig_NumberOfPlayers": 54,
    "lbl_PlayerConfigNames_PlayerName": 20,
    "lbl_points": 175,
    "lbl_tile": 171,
    "lbl_varComboPts": 32,
    "lbl_varDiceAvailable": 28,
    "lbl_varRollCount": 29,
    "lbl_varRound": 33,
    "lblOpeningPtsNeeded": 90,
    "lblPlayersTurn": 57,
    "lblProbability": 78,
    "lblTestRoll": 52,
    "numberControl": 0,
    "Player Settings Screen": 0,
    "Rectangle1_1": 87,
    "Rectangle2": 119,
    "Rectangle2_1": 48,
    "Score History Screen": 0,
    "Scoring Settings Screen": 0,
    "Screen1": 0,
    "shp_PlayerConfigNames_Separator": 22,
    "shp_StartScreen_Background": 8,
    "shpLastRoundMessageBackground": 1,
    "shpRollEndMarker": 73,
    "tbNumber": 168,
    "TextInput1": 125,
    "TextInput1_1": 144,
    "tglEnabled": 126,
    "tglEnabled_1": 145,
    "tglTestRoll_1": 51,
    "tmr_clicked": 173,
    "tmr_Farkle": 17,
    "tmr_RollTimer": 86,
    "txt_PlayerConfigNames_PlayerName": 21,
    "txtPlayerName": 134,
    "txtPlayerName_1": 151,
    "txtTestRoll_1": 49
  },
  "ResourcesJsonIndices": {
    "Audio-SampleAudio": 2,
    "Image-bkgd_City": 4,
    "Image-cozy_living_room-wallpaper-1920x1080": 5,
    "Image-SampleImage": 0,
    "Image-Table": 6,
    "Pdf-SamplePdf": 3,
    "Video-SampleVideo": 1
  },
  "RuleScreenIdWithoutScreen": {},
  "TemplateVersions": {},
  "VolatileProperties": {
    "AnalysisLoadTime": 1.8520597,
    "ControlCount": {
      "2ee30dc81626408eb5290d2c037559d5": 2,
      "346ab8d173664f849d62fb9f8ca81e51": 1,
      "4fb8b76ca030427cbb8e5cb52552fedb": 2,
      "button": 29,
      "circle": 1,
      "dropdown": 2,
      "gallery": 17,
      "galleryTemplate": 17,
      "group": 12,
      "htmlViewer": 3,
      "icon": 16,
      "image": 3,
      "label": 52,
      "rectangle": 7,
      "screen": 6,
      "star": 2,
      "text": 7,
      "timer": 3,
      "toggleSwitch": 3
    },
    "DeserializationLoadTime": 4.1861482,
    "ErrorCount": 0
  },
  "WasLocalDatabaseReferencesEmpty": true
}